shuup_testutils/__init__.py
shuup_testutils/settings_base.py
shuup_testutils/cases/__init__.py
shuup_testutils/cases/auth.py
shuup_testutils/cases/clients.py
shuup_testutils/cases/integration.py
shuup_testutils/cases/snake.py
shuup_testutils/generators/__init__.py
shuup_testutils/generators/random.py
shuup_testutils/generators/unique.py
shuup_testutils/generators/shuup/__init__.py
shuup_testutils/generators/shuup/admin_forms.py
shuup_testutils/generators/shuup/models.py
shuup_testutils/generators/shuup/requests.py
shuup_testutils/tests/__init__.py
shuup_testutils/tests/cases/__init__.py
shuup_testutils/tests/cases/test_snake.py
shuup_testutils/tests/generators/__init__.py
shuup_testutils/tests/generators/test_unique.py
shuup_testutils/tests/generators/shuup/__init__.py
shuup_testutils/tests/generators/shuup/test_admin_forms.py
shuup_testutils/tests/generators/shuup/test_models.py
shuup_testutils/tests/testproject/__init__.py
shuup_testutils/tests/testproject/manage.py
shuup_testutils/tests/testproject/settings.py
shuup_testutils-0.12.0.0.dist-info/DESCRIPTION.rst
shuup_testutils-0.12.0.0.dist-info/METADATA
shuup_testutils-0.12.0.0.dist-info/RECORD
shuup_testutils-0.12.0.0.dist-info/WHEEL
shuup_testutils-0.12.0.0.dist-info/metadata.json
shuup_testutils-0.12.0.0.dist-info/top_level.txt
